arcgpt/__init__.py
arcgpt/agent.py
arcgpt/arcgpt.py
arcgpt/openai_services.py
arcgpt/tools.py
arcgpt-0.1.2.dist-info/entry_points.txt
arcgpt-0.1.2.dist-info/METADATA
arcgpt-0.1.2.dist-info/WHEEL
arcgpt-0.1.2.dist-info/RECORD
