Metadata-Version: 2.1
Name: arcgpt
Version: 0.1.2
Summary: A ChatGPT powered library for controling ArcGIS Pro using natural language prompts.
Author: Nicholas Chai
Author-email: nicholas.chai@ngis.com.au
Requires-Python: >=3.9.16,<4.0.0
Classifier: Programming Language :: Python :: 3
Classifier: Programming Language :: Python :: 3.10
Classifier: Programming Language :: Python :: 3.11
Classifier: Programming Language :: Python :: 3.12
Requires-Dist: openai (>=1.8.0,<2.0.0)
Requires-Dist: python-dotenv (>=1.0.0,<2.0.0)
